checkpipe/__init__.py
checkpipe/checkpipe.py
checkpipe/py.typed
checkpipe-1.0.22.dist-info/METADATA
checkpipe-1.0.22.dist-info/WHEEL
checkpipe-1.0.22.dist-info/licenses/LICENSE
checkpipe-1.0.22.dist-info/RECORD
