Metadata-Version: 2.4
Name: checkpipe
Version: 1.0.22
Summary: Brings functional programming data pipelines with robust validation to python and mypy
Author-email: Mohammed Alzakariya <lanhikarixx@gmail.com>
License-File: LICENSE
Classifier: License :: OSI Approved :: MIT License
Classifier: Operating System :: OS Independent
Classifier: Programming Language :: Python :: 3
Requires-Python: >=3.8
Requires-Dist: result
